Growl.py
growlImage.m
libgrowl.c
setup.py
py_Growl.egg-info/PKG-INFO
py_Growl.egg-info/SOURCES.txt
py_Growl.egg-info/dependency_links.txt
py_Growl.egg-info/native_libs.txt
py_Growl.egg-info/top_level.txt