Metadata-Version: 1.0
Name: py-Growl
Version: 0.0.7
Summary: Python bindings for posting notifications to the Growl daemon
Home-page: http://www.assembla.com/spaces/nosegrowl/
Author: Victor Ng
Author-email: bdash@users.sourceforge.net
License: UNKNOWN
Platform: UNKNOWN
